aliyun_exporter/QueryMetricMetaRequest.py
aliyun_exporter/QueryProjectMetaRequest.py
aliyun_exporter/__init__.py
aliyun_exporter/__main__.py
aliyun_exporter/collector.py
aliyun_exporter/info_provider.py
aliyun_exporter/test_utils.py
aliyun_exporter/utils.py
aliyun_exporter/web.py
aliyun_exporter/static/style.css
aliyun_exporter/templates/detail.html
aliyun_exporter/templates/error.html
aliyun_exporter/templates/index.html
aliyun_exporter/templates/yaml.html
aliyun_exporter-0.3.1.dist-info/LICENSE
aliyun_exporter-0.3.1.dist-info/METADATA
aliyun_exporter-0.3.1.dist-info/WHEEL
aliyun_exporter-0.3.1.dist-info/entry_points.txt
aliyun_exporter-0.3.1.dist-info/top_level.txt
aliyun_exporter-0.3.1.dist-info/RECORD
