Metadata-Version: 2.1
Name: aliyun-exporter
Version: 0.3.1
Summary: Alibaba Cloud CloudMonitor Prometheus exporter
Home-page: https://github.com/aylei/aliyun-exporter
Author: Aylei Wu
Author-email: rayingecho@gmail.com
License: Apache 2.0
Keywords: monitoring prometheus exporter aliyun alibaba cloudmonitor
Platform: UNKNOWN
Classifier: Intended Audience :: Developers
Classifier: Intended Audience :: System Administrators
Classifier: Topic :: System :: Monitoring
Classifier: License :: OSI Approved :: Apache Software License
Classifier: Programming Language :: Python :: 3
Classifier: Programming Language :: Python :: 3.7
Requires-Dist: prometheus-client
Requires-Dist: aliyun-python-sdk-cms (==6.0.13)
Requires-Dist: aliyun-python-sdk-core-v3 (==2.13.3)
Requires-Dist: pyyaml
Requires-Dist: ratelimiter
Requires-Dist: flask
Requires-Dist: cachetools
Requires-Dist: aliyun-python-sdk-ecs (==4.16.5)
Requires-Dist: aliyun-python-sdk-rds (==2.3.2)
Requires-Dist: aliyun-python-sdk-r-kvstore (==2.0.5)
